keybaseclient/raw_api.py
keybaseclient/__init__.py
python_keybase_client-0.1.0.dist-info/DESCRIPTION.rst
python_keybase_client-0.1.0.dist-info/METADATA
python_keybase_client-0.1.0.dist-info/pydist.json
python_keybase_client-0.1.0.dist-info/RECORD
python_keybase_client-0.1.0.dist-info/top_level.txt
python_keybase_client-0.1.0.dist-info/WHEEL
