Metadata-Version: 2.0
Name: python-keybase-client
Version: 0.1.0
Summary: Python client for interacting with the Keybase.io API
Home-page: https://github.com/adamldoyle/python-keybase-client
Author: Adam Doyle
Author-email: adamldoyle@gmail.com
License: BSD
Keywords: python-keybase-client
Platform: UNKNOWN
Classifier: Development Status :: 2 - Pre-Alpha
Classifier: Intended Audience :: Developers
Classifier: License :: OSI Approved :: BSD License
Classifier: Natural Language :: English
Classifier: Programming Language :: Python :: 2
Classifier: Programming Language :: Python :: 2.6
Classifier: Programming Language :: Python :: 2.7
Classifier: Programming Language :: Python :: 3
Classifier: Programming Language :: Python :: 3.3
Requires-Dist: wheel (==0.22.0)
Requires-Dist: requests (==2.2.1)
Requires-Dist: scrypt (==0.6.1)
